setup.py
distributions_sm_udacity/Binomialdistribution.py
distributions_sm_udacity/Gaussiandistribution.py
distributions_sm_udacity/Generaldistribution.py
distributions_sm_udacity/__init__.py
distributions_sm_udacity.egg-info/PKG-INFO
distributions_sm_udacity.egg-info/SOURCES.txt
distributions_sm_udacity.egg-info/dependency_links.txt
distributions_sm_udacity.egg-info/not-zip-safe
distributions_sm_udacity.egg-info/top_level.txt