Metadata-Version: 1.0
Name: distributions-sm-udacity
Version: 0.1
Summary: Gaussian distributions
Home-page: UNKNOWN
Author: smilchsack
Author-email: UNKNOWN
License: UNKNOWN
Platform: UNKNOWN
